Aeros/Request.py
Aeros/WebServer.py
Aeros/__init__.py
Aeros/caching.py
Aeros/compression.py
Aeros/misc.py
Aeros/threading.py
Aeros/patches/__init__.py
Aeros/patches/flask_caching/Cache.py
Aeros/patches/flask_caching/__init__.py
Aeros/patches/hypercorn/Config.py
Aeros/patches/hypercorn/__init__.py
Aeros/patches/hypercorn/run.py
Aeros/patches/hypercorn/worker.py
Aeros/patches/quart/__init__.py
Aeros/patches/quart/app.py
Aeros/patches/quart/asgi.py
Aeros-1.1.0.dist-info/METADATA
Aeros-1.1.0.dist-info/WHEEL
Aeros-1.1.0.dist-info/top_level.txt
Aeros-1.1.0.dist-info/RECORD
