Metadata-Version: 2.1
Name: Aeros
Version: 1.1.0
Summary: High-performance ASGI framework
Home-page: https://gitlab.com/wiesen.leon/aeros
Author: Leon Wiesen
License: UNKNOWN
Platform: UNKNOWN
Classifier: Programming Language :: Python :: 3.6
Classifier: License :: OSI Approved :: GNU General Public License v3 (GPLv3)
Classifier: Operating System :: OS Independent
Requires-Python: >=3.6
Requires-Dist: asgiref (>=3.2.7)
Requires-Dist: hypercorn (>=0.9.5)
Requires-Dist: quart (>=0.11.5)
Requires-Dist: aioquic
Requires-Dist: quart-compress
Requires-Dist: flask-caching
